pywhatsapp/__init__.py
pywhatsapp/pywhatsapp.py
pywhatmessage-0.0.1.dist-info/METADATA
pywhatmessage-0.0.1.dist-info/WHEEL
pywhatmessage-0.0.1.dist-info/top_level.txt
pywhatmessage-0.0.1.dist-info/RECORD
