Metadata-Version: 2.1
Name: pywhatmessage
Version: 0.0.1
Summary: Send whatsapp messages
Home-page: UNKNOWN
Author: Sabaris
Author-email: spssabaris@gmail.com
License: UNKNOWN
Keywords: python,whatsapp,message,whatmessage,whatmsg,automation
Platform: UNKNOWN
Classifier: Programming Language :: Python :: 3
Classifier: Operating System :: Unix
Classifier: Operating System :: MacOS :: MacOS X
Classifier: Operating System :: Microsoft :: Windows
Requires-Dist: time
Requires-Dist: webbrowser
Requires-Dist: datetime
Requires-Dist: typing
Requires-Dist: urllib
Requires-Dist: pyautogui
Requires-Dist: pywhatkit
